runyx_bridge/__init__.py
runyx_bridge/app.py
runyx_bridge/bridge.py
runyx_bridge/browser.py
runyx_bridge/decorators.py
runyx_bridge/extension.py
runyx_bridge/http_server.py
runyx_bridge/README.md
runyx_bridge/websocket_sender.py
runyx_bridge/websocket_server.py
runyx-1.0.3.dist-info/LICENSE
runyx-1.0.3.dist-info/METADATA
runyx-1.0.3.dist-info/WHEEL
runyx-1.0.3.dist-info/RECORD
