Metadata-Version: 2.1
Name: runyx
Version: 1.0.3
Summary: Local bridge for Runyx extension
Home-page: https://github.com/Guiflayrom/runyx
License: MIT
Keywords: runyx,bridge,automation,selenium,websocket
Author: Guiflayrom
Author-email: guiflayrom@gmail.com
Requires-Python: >=3.12,<4.0
Classifier: Development Status :: 3 - Alpha
Classifier: Intended Audience :: Developers
Classifier: License :: OSI Approved :: MIT License
Classifier: Programming Language :: Python :: 3
Classifier: Programming Language :: Python :: 3.12
Classifier: Programming Language :: Python :: 3 :: Only
Requires-Dist: colorama (>=0.4.6,<0.5.0)
Requires-Dist: flask (>=3.1.2,<4.0.0)
Requires-Dist: pyautogui (>=0.9.54,<0.10.0)
Requires-Dist: selenium (>=4.39.0,<5.0.0)
Requires-Dist: websockets (>=15.0.1,<16.0.0)
Project-URL: Documentation, https://github.com/Guiflayrom/runyx#readme
Project-URL: Repository, https://github.com/Guiflayrom/runyx
